{
	"id": "callcard-public-dns",
	"name": "CallCard - Public DNS (HTTPS)",
	"values": [
		{
			"key": "base_url",
			"value": "https://talosmaind.saicongames.com/callcard",
			"type": "default",
			"enabled": true
		},
		{
			"key": "jwt_token",
			"value": "",
			"type": "secret",
			"enabled": true
		},
		{
			"key": "callcard_id",
			"value": "1",
			"type": "default",
			"enabled": true
		},
		{
			"key": "user_id",
			"value": "1",
			"type": "default",
			"enabled": true
		}
	],
	"_postman_variable_scope": "environment"
}